{
  "parent": "minecraft:recipes/root",
  "criteria": {
    "has_gold_nugget": {
      "conditions": {
        "items": [
          {
            "items": [
              "minecraft:gold_nugget"
            ]
          }
        ]
      },
      "trigger": "minecraft:inventory_changed"
    },
    "has_handheld_tube": {
      "conditions": {
        "items": [
          {
            "items": [
              "let:handheld_tube"
            ]
          }
        ]
      },
      "trigger": "minecraft:inventory_changed"
    },
    "has_light_blue_dye": {
      "conditions": {
        "items": [
          {
            "items": [
              "minecraft:light_blue_dye"
            ]
          }
        ]
      },
      "trigger": "minecraft:inventory_changed"
    },
    "has_shade": {
      "conditions": {
        "items": [
          {
            "items": [
              "let:shade"
            ]
          }
        ]
      },
      "trigger": "minecraft:inventory_changed"
    },
    "has_the_recipe": {
      "conditions": {
        "recipe": "let:crafting/detector_light_blue"
      },
      "trigger": "minecraft:recipe_unlocked"
    }
  },
  "requirements": [
    [
      "has_handheld_tube",
      "has_shade",
      "has_gold_nugget",
      "has_light_blue_dye",
      "has_the_recipe"
    ]
  ],
  "rewards": {
    "recipes": [
      "let:crafting/detector_light_blue"
    ]
  },
  "sends_telemetry_event": false
}